deutschland/berufssprachkurssuche/__init__.py
deutschland/berufssprachkurssuche/api/__init__.py
deutschland/berufssprachkurssuche/api/default_api.py
deutschland/berufssprachkurssuche/api_client.py
deutschland/berufssprachkurssuche/apis/__init__.py
deutschland/berufssprachkurssuche/configuration.py
deutschland/berufssprachkurssuche/exceptions.py
deutschland/berufssprachkurssuche/model/__init__.py
deutschland/berufssprachkurssuche/model/response.py
deutschland/berufssprachkurssuche/model/response_embedded.py
deutschland/berufssprachkurssuche/model/response_embedded_abstaende.py
deutschland/berufssprachkurssuche/model/response_embedded_adresse.py
deutschland/berufssprachkurssuche/model/response_embedded_adresse_koordinaten.py
deutschland/berufssprachkurssuche/model/response_embedded_aggregations.py
deutschland/berufssprachkurssuche/model/response_embedded_aggregations_anbieter.py
deutschland/berufssprachkurssuche/model/response_embedded_aggregations_anzahlausgefiltert.py
deutschland/berufssprachkurssuche/model/response_embedded_aggregations_anzahlgesamt.py
deutschland/berufssprachkurssuche/model/response_embedded_aggregations_beginntermin.py
deutschland/berufssprachkurssuche/model/response_embedded_aggregations_regionen.py
deutschland/berufssprachkurssuche/model/response_embedded_aggregations_sprachkurse.py
deutschland/berufssprachkurssuche/model/response_embedded_aggregations_unterrichtsformen.py
deutschland/berufssprachkurssuche/model/response_embedded_angebot.py
deutschland/berufssprachkurssuche/model/response_embedded_angebot_bildungsanbieter.py
deutschland/berufssprachkurssuche/model/response_embedded_angebot_bildungsanbieter_adresse.py
deutschland/berufssprachkurssuche/model/response_embedded_angebot_bildungsanbieter_adresse_koordinaten.py
deutschland/berufssprachkurssuche/model/response_embedded_angebot_bildungsanbieter_adresse_ort_strasse.py
deutschland/berufssprachkurssuche/model/response_embedded_angebot_bildungsanbieter_adresse_ort_strasse_land.py
de_berufssprachkurssuche-0.1.0.dist-info/WHEEL
de_berufssprachkurssuche-0.1.0.dist-info/METADATA
de_berufssprachkurssuche-0.1.0.dist-info/RECORD
